poc_publish/__init__.py
poc_publish/pretty.py
poc_publish-0.1.0.dist-info/WHEEL
poc_publish-0.1.0.dist-info/METADATA
poc_publish-0.1.0.dist-info/RECORD
