Metadata-Version: 2.1
Name: poc-publish
Version: 0.1.0
Summary: 
Author: Gláuber Brennon
Author-email: glauberbrennon@gmail.com
Requires-Python: >=3.9,<4.0
Classifier: Programming Language :: Python :: 3
Classifier: Programming Language :: Python :: 3.9
Requires-Dist: black (>=21.5b1,<22.0)
Requires-Dist: mypy (>=0.812,<0.813)
Requires-Dist: pyfiglet (>=0.8.post1,<0.9)
Requires-Dist: termcolor (>=1.1.0,<2.0.0)
